Metadata-Version: 2.1
Name: junit-to-md-py
Version: 1.1.0
Summary: Python script which converts junit xml file/text into the markdown representation
Home-page: https://github.com/catalogicsoftware/dpx-utils-junit-to-md
Author: srydz_catalogicsoftware
Author-email: srydz@catalogicsoftware.com
License: MIT
